holes/__init__.py
holes/_version.py
holes/ret.py
holes/tests/__init__.py
holes/tests/conftest.py
holes/tests/test_examples.py
holes-0.1.0.dist-info/AUTHORS.rst
holes-0.1.0.dist-info/LICENSE
holes-0.1.0.dist-info/METADATA
holes-0.1.0.dist-info/WHEEL
holes-0.1.0.dist-info/entry_points.txt
holes-0.1.0.dist-info/top_level.txt
holes-0.1.0.dist-info/RECORD
