Metadata-Version: 2.1
Name: holes
Version: 0.1.0
Summary: Python package for doing science.
Home-page: https://github.com/DouglasCAllan/holes
Author: Douglas Allan
Author-email: physics.dance@gmail.com
License: BSD (3-clause)
Platform: UNKNOWN
Classifier: Development Status :: 2 - Pre-Alpha
Classifier: Natural Language :: English
Classifier: Programming Language :: Python :: 3
Requires-Dist: numpy
Requires-Dist: matplotlib
